{
  "vpc-provider:account=111111111111:filter.vpc-id=vpc-11111111111111111:region=us-east-1:returnAsymmetricSubnets=true": {
    "vpcId": "vpc-11111111111111111",
    "availabilityZones": [
      "us-east-1a",
      "us-east-1b"
    ],
    "subnetGroups": [
      {
        "name": "Public",
        "type": "Public",
        "subnets": [
          {
            "availabilityZone": "us-east-1a",
            "subnetId": "s-12345",
            "routeTableId": "rtb-12345s"
          },
          {
            "availabilityZone": "us-east-1b",
            "subnetId": "s-67890",
            "routeTableId": "rtb-67890s"
          }
        ]
      },
      {
        "name": "Private",
        "type": "Private",
        "subnets": [
          {
            "availabilityZone": "us-east-1a",
            "subnetId": "p-12345",
            "routeTableId": "rtb-12345p"
          },
          {
            "availabilityZone": "us-east-1b",
            "subnetId": "p-67890",
            "routeTableId": "rtb-57890p"
          }
        ]
      }
    ]
  }
}
